ddcDatabases/.env.example
ddcDatabases/__init__.py
ddcDatabases/db_utils.py
ddcDatabases/exceptions.py
ddcDatabases/mongodb.py
ddcDatabases/mssql.py
ddcDatabases/mysql.py
ddcDatabases/oracle.py
ddcDatabases/postgresql.py
ddcDatabases/settings.py
ddcDatabases/sqlite.py
ddcdatabases-2.0.8.dist-info/METADATA
ddcdatabases-2.0.8.dist-info/WHEEL
ddcdatabases-2.0.8.dist-info/licenses/LICENSE
ddcdatabases-2.0.8.dist-info/RECORD
