Metadata-Version: 2.4
Name: ddcDatabases
Version: 2.0.8
Summary: Simplified Database ORM Connections
License: MIT
License-File: LICENSE
Keywords: python3,python-3,python,databases,database,ddcDatabases,mongodb,mongodb-database,mssql,mssql-database,mysql,mysql-database,oracle,oracle-database,pgsql,postgres,postgresql,postgressql,postgresql-database,sqlite,sqlite3,sqlite3-database
Author: Daniel Costa
Author-email: danieldcsta@gmail.com
Maintainer: Daniel Costa
Requires-Python: >=3.12,<4.0
Classifier: Development Status :: 5 - Production/Stable
Classifier: Environment :: Other Environment
Classifier: Intended Audience :: Developers
Classifier: License :: OSI Approved :: MIT License
Classifier: Natural Language :: English
Classifier: Operating System :: OS Independent
Classifier: Programming Language :: Python :: 3
Classifier: Programming Language :: Python :: 3.12
Classifier: Programming Language :: Python :: 3.13
Classifier: Programming Language :: Python :: 3.14
Classifier: Programming Language :: Python :: 3 :: Only
Classifier: Topic :: Software Development :: Libraries :: Python Modules
Provides-Extra: all
Provides-Extra: mongodb
Provides-Extra: mssql
Provides-Extra: mysql
Provides-Extra: oracle
Provides-Extra: pgsql
Requires-Dist: aiomysql (>=0.2.0,<0.3.0) ; extra == "mysql" or extra == "all"
Requires-Dist: aioodbc (>=0.5.0,<0.6.0) ; extra == "mssql" or extra == "all"
Requires-Dist: asyncpg (>=0.30.0,<0.31.0) ; extra == "pgsql" or extra == "all"
Requires-Dist: cx-oracle (>=8.3.0,<9.0.0) ; extra == "oracle" or extra == "all"
Requires-Dist: greenlet (>=3.2.4,<4.0.0)
Requires-Dist: psycopg2-binary (>=2.9.10,<3.0.0) ; extra == "pgsql" or extra == "all"
Requires-Dist: pydantic-settings (>=2.10.1,<3.0.0)
Requires-Dist: pymongo (>=4.15.1,<5.0.0) ; extra == "mongodb" or extra == "all"
Requires-Dist: pymysql (>=1.1.2,<2.0.0) ; extra == "mysql" or extra == "all"
Requires-Dist: pyodbc (>=5.2.0,<6.0.0) ; extra == "mssql" or extra == "all"
Requires-Dist: sqlalchemy (>=2.0.43,<3.0.0)
Project-URL: Homepage, https://pypi.org/project/ddcDatabases
Project-URL: Repository, https://github.com/ddc/ddcDatabases
